reportracingtable/__init__.py
reportracingtable/app/__init__.py
reportracingtable/app/app.py
reportracingtable/utils/__init__.py
reportracingtable/utils/exceptions.py
reportracingtable/utils/functions.py
reportracingtable/utils/utilitys.py
reportracingtable-1.0.0.dist-info/LICENSE
reportracingtable-1.0.0.dist-info/METADATA
reportracingtable-1.0.0.dist-info/WHEEL
reportracingtable-1.0.0.dist-info/entry_points.txt
reportracingtable-1.0.0.dist-info/top_level.txt
reportracingtable-1.0.0.dist-info/RECORD
