Metadata-Version: 2.1
Name: reportracingtable
Version: 1.0.0
Summary: Generate Monaco Racing report
Home-page: UNKNOWN
Author: Dihtiar Vadym
License: UNKNOWN
Platform: UNKNOWN
Requires-Python: >=3.8
License-File: LICENSE
Requires-Dist: texttable (==1.6.7)
